batch_queue-0.6.data/scripts/queue
queue_server/__init__.py
queue_server/queue.tac
queue_server/server.py
queue_server/task.py
batch_queue-0.6.dist-info/METADATA
batch_queue-0.6.dist-info/WHEEL
batch_queue-0.6.dist-info/top_level.txt
batch_queue-0.6.dist-info/RECORD
