Metadata-Version: 2.1
Name: batch-queue
Version: 0.6
Summary: simple batch queuing system
Home-page: http://code.google.com/p/batch-queue/
Author: Neal Becker
Author-email: ndbecker2@gmail.com
Requires-Dist: twisted
